LICENSE.md
README.md
setup.cfg
setup.py
celsius_python_sdk.egg-info/PKG-INFO
celsius_python_sdk.egg-info/SOURCES.txt
celsius_python_sdk.egg-info/dependency_links.txt
celsius_python_sdk.egg-info/requires.txt
celsius_python_sdk.egg-info/top_level.txt
pyCelsius/__init__.py
pyCelsius/__main__.py
pyCelsius/celsius_api.py
pyCelsius/const.py
pyCelsius/version.py