Metadata-Version: 2.1
Name: celsius-python-sdk
Version: 1.0.1
Summary: Celsius API SDK for Python
Home-page: https://github.com/rguarascia/Celsius-App-API-Kit/tree/master/python/celsius-python-sdk
Author: Raag Naidu
Author-email: raag.naidu@gmail.com
License: MIT
Platform: UNKNOWN
Classifier: Development Status :: 5 - Production/Stable
Classifier: Intended Audience :: Developers
Classifier: License :: OSI Approved :: MIT License
Classifier: Operating System :: OS Independent
Classifier: Topic :: Software Development :: Libraries :: Python Modules
Classifier: Programming Language :: Python :: 3
Classifier: Programming Language :: Python :: 3.6
Classifier: Programming Language :: Python :: 3.7
Classifier: Programming Language :: Python :: 3.8
